{"mtime_ns":1772211642519480957,"size":11344,"module_info":{"file_path":"/home/mk/projects/Demarch/research/beads_rust/tests/proptest_time.rs","language":"rust","docstring":null,"imports":[{"module":"chrono::{DateTime, Datelike, Duration, Timelike, Utc}","names":[],"is_from":false,"line_number":9},{"module":"proptest::prelude::*","names":[],"is_from":false,"line_number":10},{"module":"tracing::info","names":[],"is_from":false,"line_number":11},{"module":"beads_rust::util::time::{parse_flexible_timestamp, parse_relative_time}","names":[],"is_from":false,"line_number":13}],"classes":[],"functions":[{"name":"init_test_logging","params":[],"return_type":null,"docstring":null,"is_method":false,"is_async":false,"decorators":[],"line_number":16,"language":"rust"},{"name":"keyword_tomorrow_is_future","params":[],"return_type":null,"docstring":null,"is_method":false,"is_async":false,"decorators":[],"line_number":259,"language":"rust"},{"name":"keyword_next_week_is_week_away","params":[],"return_type":null,"docstring":null,"is_method":false,"is_async":false,"decorators":[],"line_number":284,"language":"rust"},{"name":"rfc3339_with_offset_parses","params":[],"return_type":null,"docstring":null,"is_method":false,"is_async":false,"decorators":[],"line_number":307,"language":"rust"},{"name":"whitespace_is_trimmed","params":[],"return_type":null,"docstring":null,"is_method":false,"is_async":false,"decorators":[],"line_number":331,"language":"rust"}],"call_graph":{"calls":{"keyword_tomorrow_is_future":["init_test_logging"],"keyword_next_week_is_week_away":["init_test_logging"],"rfc3339_with_offset_parses":["init_test_logging"],"whitespace_is_trimmed":["init_test_logging"]},"called_by":{"init_test_logging":["keyword_tomorrow_is_future","keyword_next_week_is_week_away","rfc3339_with_offset_parses","whitespace_is_trimmed"]}}}}