{"mtime_ns":1772149684688598035,"size":3857,"module_info":{"file_path":"/home/mk/projects/Demarch/core/interbench/tests/test_interbench.py","language":"python","docstring":"Smoke tests for interbench CLI.","imports":[{"module":"json","names":[],"is_from":false,"line_number":3},{"module":"os","names":[],"is_from":false,"line_number":4},{"module":"sqlite3","names":[],"is_from":false,"line_number":5},{"module":"subprocess","names":[],"is_from":false,"line_number":6},{"module":"sys","names":[],"is_from":false,"line_number":7},{"module":"tempfile","names":[],"is_from":false,"line_number":8},{"module":"pathlib","names":["Path"],"is_from":true,"line_number":9}],"classes":[{"name":"TestRun","bases":[],"docstring":null,"methods":[{"name":"test_basic_capture","params":["self","tmp_path"],"return_type":null,"docstring":null,"is_method":true,"is_async":false,"decorators":[],"line_number":32,"language":"python"},{"name":"test_failing_command","params":["self","tmp_path"],"return_type":null,"docstring":null,"is_method":true,"is_async":false,"decorators":[],"line_number":54,"language":"python"},{"name":"test_metadata","params":["self","tmp_path"],"return_type":null,"docstring":null,"is_method":true,"is_async":false,"decorators":[],"line_number":63,"language":"python"},{"name":"test_events_recorded","params":["self","tmp_path"],"return_type":null,"docstring":null,"is_method":true,"is_async":false,"decorators":[],"line_number":72,"language":"python"},{"name":"test_content_dedup","params":["self","tmp_path"],"return_type":null,"docstring":"Same output produces same blob (content-addressed).","is_method":true,"is_async":false,"decorators":[],"line_number":79,"language":"python"}],"decorators":[],"line_number":31},{"name":"TestList","bases":[],"docstring":null,"methods":[{"name":"test_empty","params":["self","tmp_path"],"return_type":null,"docstring":null,"is_method":true,"is_async":false,"decorators":[],"line_number":96,"language":"python"},{"name":"test_shows_runs","params":["self","tmp_path"],"return_type":null,"docstring":null,"is_method":true,"is_async":false,"decorators":[],"line_number":100,"language":"python"}],"decorators":[],"line_number":95},{"name":"TestShow","bases":[],"docstring":null,"methods":[{"name":"test_show_run","params":["self","tmp_path"],"return_type":null,"docstring":null,"is_method":true,"is_async":false,"decorators":[],"line_number":108,"language":"python"},{"name":"test_show_missing","params":["self","tmp_path"],"return_type":null,"docstring":null,"is_method":true,"is_async":false,"decorators":[],"line_number":118,"language":"python"}],"decorators":[],"line_number":107}],"functions":[{"name":"run_cli","params":["*args","home = None"],"return_type":null,"docstring":null,"is_method":false,"is_async":false,"decorators":[],"line_number":14,"language":"python"},{"name":"db","params":["home"],"return_type":null,"docstring":null,"is_method":false,"is_async":false,"decorators":[],"line_number":25,"language":"python"}],"call_graph":{"calls":{"TestRun.test_basic_capture":["run_cli","db"],"TestRun.test_failing_command":["run_cli","db"],"TestRun.test_metadata":["run_cli","db"],"TestRun.test_events_recorded":["run_cli","db"],"TestRun.test_content_dedup":["run_cli","db"],"TestList.test_empty":["run_cli"],"TestList.test_shows_runs":["run_cli"],"TestShow.test_show_run":["run_cli","db"],"TestShow.test_show_missing":["run_cli"]},"called_by":{"run_cli":["TestRun.test_basic_capture","TestRun.test_failing_command","TestRun.test_metadata","TestRun.test_events_recorded","TestRun.test_content_dedup","TestList.test_empty","TestList.test_shows_runs","TestShow.test_show_run","TestShow.test_show_missing"],"db":["TestRun.test_basic_capture","TestRun.test_failing_command","TestRun.test_metadata","TestRun.test_events_recorded","TestRun.test_content_dedup","TestShow.test_show_run"]}}}}