{"mtime_ns":1772211651785481812,"size":38445,"module_info":{"file_path":"/home/mk/projects/Demarch/research/frankensearch/crates/frankensearch-fusion/src/calibration.rs","language":"rust","docstring":null,"imports":[{"module":"serde::{Deserialize, Serialize}","names":[],"is_from":false,"line_number":28},{"module":"super::*","names":[],"is_from":false,"line_number":585},{"module":"tracing_test::traced_test","names":[],"is_from":false,"line_number":586}],"classes":[{"name":"trait ScoreCalibrator","bases":[],"docstring":null,"methods":[{"name":"calibrate","params":[],"return_type":null,"docstring":null,"is_method":true,"is_async":false,"decorators":[],"line_number":41,"language":"python"},{"name":"name","params":[],"return_type":null,"docstring":null,"is_method":true,"is_async":false,"decorators":[],"line_number":53,"language":"python"}],"decorators":[],"line_number":39},{"name":"Identity","bases":[],"docstring":null,"methods":[],"decorators":[],"line_number":63},{"name":"TemperatureScaling","bases":[],"docstring":null,"methods":[],"decorators":[],"line_number":91},{"name":"PlattScaling","bases":[],"docstring":null,"methods":[],"decorators":[],"line_number":138},{"name":"IsotonicRegression","bases":[],"docstring":null,"methods":[],"decorators":[],"line_number":196},{"name":"CalibrationSummary","bases":[],"docstring":null,"methods":[],"decorators":[],"line_number":464}],"functions":[{"name":"(Identity) calibrate","params":["&self","raw_score: f64"],"return_type":"f64","docstring":null,"is_method":true,"is_async":false,"decorators":[],"line_number":66,"language":"rust"},{"name":"(Identity) name","params":["&self"],"return_type":"&'static str","docstring":null,"is_method":true,"is_async":false,"decorators":[],"line_number":73,"language":"rust"},{"name":"(TemperatureScaling) new","params":["temperature: f64"],"return_type":"Self","docstring":null,"is_method":true,"is_async":false,"decorators":[],"line_number":103,"language":"rust"},{"name":"(TemperatureScaling) calibrate","params":["&self","raw_score: f64"],"return_type":"f64","docstring":null,"is_method":true,"is_async":false,"decorators":[],"line_number":113,"language":"rust"},{"name":"(TemperatureScaling) name","params":["&self"],"return_type":"&'static str","docstring":null,"is_method":true,"is_async":false,"decorators":[],"line_number":120,"language":"rust"},{"name":"(PlattScaling) new","params":["a: f64","b: f64"],"return_type":"Self","docstring":null,"is_method":true,"is_async":false,"decorators":[],"line_number":152,"language":"rust"},{"name":"(PlattScaling) calibrate","params":["&self","raw_score: f64"],"return_type":"f64","docstring":null,"is_method":true,"is_async":false,"decorators":[],"line_number":162,"language":"rust"},{"name":"(PlattScaling) name","params":["&self"],"return_type":"&'static str","docstring":null,"is_method":true,"is_async":false,"decorators":[],"line_number":169,"language":"rust"},{"name":"(IsotonicRegression) new","params":["breakpoints: Vec<f64>","values: Vec<f64>"],"return_type":"Self","docstring":null,"is_method":true,"is_async":false,"decorators":[],"line_number":215,"language":"rust"},{"name":"(IsotonicRegression) fit","params":["scores: &[f64]","labels: &[f64]"],"return_type":"Self","docstring":null,"is_method":true,"is_async":false,"decorators":[],"line_number":268,"language":"rust"},{"name":"(IsotonicRegression) calibrate","params":["&self","raw_score: f64"],"return_type":"f64","docstring":null,"is_method":true,"is_async":false,"decorators":[],"line_number":321,"language":"rust"},{"name":"(IsotonicRegression) name","params":["&self"],"return_type":"&'static str","docstring":null,"is_method":true,"is_async":false,"decorators":[],"line_number":337,"language":"rust"},{"name":"compute_ece","params":["predictions: &[f64]","labels: &[f64]","num_bins: usize"],"return_type":"f64","docstring":null,"is_method":false,"is_async":false,"decorators":[],"line_number":363,"language":"rust"},{"name":"compute_brier_score","params":["predictions: &[f64]","labels: &[f64]"],"return_type":"f64","docstring":null,"is_method":false,"is_async":false,"decorators":[],"line_number":402,"language":"rust"},{"name":"(CalibratorConfig) as_calibrator","params":["&self"],"return_type":"&dyn ScoreCalibrator","docstring":null,"is_method":true,"is_async":false,"decorators":[],"line_number":440,"language":"rust"},{"name":"(CalibratorConfig) calibrate","params":["&self","raw_score: f64"],"return_type":"f64","docstring":null,"is_method":true,"is_async":false,"decorators":[],"line_number":451,"language":"rust"},{"name":"(CalibratorConfig) name","params":["&self"],"return_type":"&str","docstring":null,"is_method":true,"is_async":false,"decorators":[],"line_number":457,"language":"rust"},{"name":"calibrate_scores_with_labels","params":["calibrator: &dyn ScoreCalibrator","raw_scores: &[f64]","labels: &[f64]","num_bins: usize"],"return_type":"(Vec<f64>, CalibrationSummary)","docstring":null,"is_method":false,"is_async":false,"decorators":[],"line_number":489,"language":"rust"},{"name":"sigmoid","params":["x: f64"],"return_type":"f64","docstring":null,"is_method":false,"is_async":false,"decorators":[],"line_number":564,"language":"rust"},{"name":"bounded_probability","params":["value: f64"],"return_type":"f64","docstring":null,"is_method":false,"is_async":false,"decorators":[],"line_number":576,"language":"rust"},{"name":"sigmoid_zero_is_half","params":[],"return_type":null,"docstring":null,"is_method":false,"is_async":false,"decorators":[],"line_number":591,"language":"rust"},{"name":"sigmoid_large_positive_near_one","params":[],"return_type":null,"docstring":null,"is_method":false,"is_async":false,"decorators":[],"line_number":596,"language":"rust"},{"name":"sigmoid_large_negative_near_zero","params":[],"return_type":null,"docstring":null,"is_method":false,"is_async":false,"decorators":[],"line_number":601,"language":"rust"},{"name":"sigmoid_symmetry","params":[],"return_type":null,"docstring":null,"is_method":false,"is_async":false,"decorators":[],"line_number":606,"language":"rust"},{"name":"identity_passthrough","params":[],"return_type":null,"docstring":null,"is_method":false,"is_async":false,"decorators":[],"line_number":614,"language":"rust"},{"name":"identity_clamps_out_of_range","params":[],"return_type":null,"docstring":null,"is_method":false,"is_async":false,"decorators":[],"line_number":622,"language":"rust"},{"name":"identity_handles_nan","params":[],"return_type":null,"docstring":null,"is_method":false,"is_async":false,"decorators":[],"line_number":629,"language":"rust"},{"name":"identity_handles_infinity","params":[],"return_type":null,"docstring":null,"is_method":false,"is_async":false,"decorators":[],"line_number":635,"language":"rust"},{"name":"identity_name","params":[],"return_type":null,"docstring":null,"is_method":false,"is_async":false,"decorators":[],"line_number":642,"language":"rust"},{"name":"temperature_t1_is_sigmoid","params":[],"return_type":null,"docstring":null,"is_method":false,"is_async":false,"decorators":[],"line_number":649,"language":"rust"},{"name":"temperature_higher_t_softer_output","params":[],"return_type":null,"docstring":null,"is_method":false,"is_async":false,"decorators":[],"line_number":656,"language":"rust"},{"name":"temperature_zero_input_is_half","params":[],"return_type":null,"docstring":null,"is_method":false,"is_async":false,"decorators":[],"line_number":666,"language":"rust"},{"name":"temperature_handles_nan","params":[],"return_type":null,"docstring":null,"is_method":false,"is_async":false,"decorators":[],"line_number":672,"language":"rust"},{"name":"temperature_monotonicity","params":[],"return_type":null,"docstring":null,"is_method":false,"is_async":false,"decorators":[],"line_number":678,"language":"rust"},{"name":"temperature_name","params":[],"return_type":null,"docstring":null,"is_method":false,"is_async":false,"decorators":[],"line_number":694,"language":"rust"},{"name":"temperature_rejects_zero","params":[],"return_type":null,"docstring":null,"is_method":false,"is_async":false,"decorators":[],"line_number":700,"language":"rust"},{"name":"temperature_rejects_negative","params":[],"return_type":null,"docstring":null,"is_method":false,"is_async":false,"decorators":[],"line_number":706,"language":"rust"},{"name":"platt_zero_params_is_sigmoid","params":[],"return_type":null,"docstring":null,"is_method":false,"is_async":false,"decorators":[],"line_number":713,"language":"rust"},{"name":"platt_identity_slope","params":[],"return_type":null,"docstring":null,"is_method":false,"is_async":false,"decorators":[],"line_number":720,"language":"rust"},{"name":"platt_negative_slope","params":[],"return_type":null,"docstring":null,"is_method":false,"is_async":false,"decorators":[],"line_number":728,"language":"rust"},{"name":"platt_handles_nan","params":[],"return_type":null,"docstring":null,"is_method":false,"is_async":false,"decorators":[],"line_number":739,"language":"rust"},{"name":"platt_monotonicity_positive_slope","params":[],"return_type":null,"docstring":null,"is_method":false,"is_async":false,"decorators":[],"line_number":745,"language":"rust"},{"name":"platt_name","params":[],"return_type":null,"docstring":null,"is_method":false,"is_async":false,"decorators":[],"line_number":754,"language":"rust"},{"name":"platt_rejects_nan_params","params":[],"return_type":null,"docstring":null,"is_method":false,"is_async":false,"decorators":[],"line_number":760,"language":"rust"},{"name":"isotonic_simple_step_function","params":[],"return_type":null,"docstring":null,"is_method":false,"is_async":false,"decorators":[],"line_number":767,"language":"rust"},{"name":"isotonic_interpolation_between_breakpoints","params":[],"return_type":null,"docstring":null,"is_method":false,"is_async":false,"decorators":[],"line_number":775,"language":"rust"},{"name":"isotonic_below_first_breakpoint","params":[],"return_type":null,"docstring":null,"is_method":false,"is_async":false,"decorators":[],"line_number":783,"language":"rust"},{"name":"isotonic_above_last_breakpoint","params":[],"return_type":null,"docstring":null,"is_method":false,"is_async":false,"decorators":[],"line_number":790,"language":"rust"},{"name":"isotonic_handles_nan","params":[],"return_type":null,"docstring":null,"is_method":false,"is_async":false,"decorators":[],"line_number":797,"language":"rust"},{"name":"isotonic_single_breakpoint","params":[],"return_type":null,"docstring":null,"is_method":false,"is_async":false,"decorators":[],"line_number":803,"language":"rust"},{"name":"isotonic_monotonicity_guarantee","params":[],"return_type":"","docstring":null,"is_method":false,"is_async":false,"decorators":[],"line_number":811,"language":"rust"},{"name":"isotonic_name","params":[],"return_type":null,"docstring":null,"is_method":false,"is_async":false,"decorators":[],"line_number":828,"language":"rust"},{"name":"isotonic_rejects_empty","params":[],"return_type":null,"docstring":null,"is_method":false,"is_async":false,"decorators":[],"line_number":835,"language":"rust"},{"name":"isotonic_rejects_length_mismatch","params":[],"return_type":null,"docstring":null,"is_method":false,"is_async":false,"decorators":[],"line_number":841,"language":"rust"},{"name":"isotonic_rejects_unsorted_breakpoints","params":[],"return_type":null,"docstring":null,"is_method":false,"is_async":false,"decorators":[],"line_number":847,"language":"rust"},{"name":"isotonic_rejects_non_monotonic_values","params":[],"return_type":null,"docstring":null,"is_method":false,"is_async":false,"decorators":[],"line_number":853,"language":"rust"},{"name":"isotonic_rejects_out_of_range_values","params":[],"return_type":null,"docstring":null,"is_method":false,"is_async":false,"decorators":[],"line_number":859,"language":"rust"},{"name":"isotonic_fit_perfectly_calibrated","params":[],"return_type":null,"docstring":null,"is_method":false,"is_async":false,"decorators":[],"line_number":866,"language":"rust"},{"name":"isotonic_fit_with_violations","params":[],"return_type":null,"docstring":null,"is_method":false,"is_async":false,"decorators":[],"line_number":878,"language":"rust"},{"name":"isotonic_fit_all_same_label","params":[],"return_type":null,"docstring":null,"is_method":false,"is_async":false,"decorators":[],"line_number":896,"language":"rust"},{"name":"isotonic_fit_single_point","params":[],"return_type":null,"docstring":null,"is_method":false,"is_async":false,"decorators":[],"line_number":905,"language":"rust"},{"name":"isotonic_fit_unsorted_input","params":[],"return_type":null,"docstring":null,"is_method":false,"is_async":false,"decorators":[],"line_number":912,"language":"rust"},{"name":"batch_calibration_matches_sequential","params":[],"return_type":null,"docstring":null,"is_method":false,"is_async":false,"decorators":[],"line_number":926,"language":"rust"},{"name":"ece_well_calibrated","params":[],"return_type":null,"docstring":null,"is_method":false,"is_async":false,"decorators":[],"line_number":940,"language":"rust"},{"name":"ece_completely_miscalibrated","params":[],"return_type":null,"docstring":null,"is_method":false,"is_async":false,"decorators":[],"line_number":952,"language":"rust"},{"name":"ece_empty_inputs","params":[],"return_type":null,"docstring":null,"is_method":false,"is_async":false,"decorators":[],"line_number":962,"language":"rust"},{"name":"ece_zero_bins","params":[],"return_type":null,"docstring":null,"is_method":false,"is_async":false,"decorators":[],"line_number":967,"language":"rust"},{"name":"brier_score_perfect","params":[],"return_type":null,"docstring":null,"is_method":false,"is_async":false,"decorators":[],"line_number":974,"language":"rust"},{"name":"brier_score_worst","params":[],"return_type":null,"docstring":null,"is_method":false,"is_async":false,"decorators":[],"line_number":981,"language":"rust"},{"name":"brier_score_empty","params":[],"return_type":null,"docstring":null,"is_method":false,"is_async":false,"decorators":[],"line_number":988,"language":"rust"},{"name":"calibrator_config_identity_roundtrip","params":[],"return_type":null,"docstring":null,"is_method":false,"is_async":false,"decorators":[],"line_number":995,"language":"rust"},{"name":"calibrator_config_temperature_roundtrip","params":[],"return_type":null,"docstring":null,"is_method":false,"is_async":false,"decorators":[],"line_number":1003,"language":"rust"},{"name":"calibrator_config_platt_roundtrip","params":[],"return_type":null,"docstring":null,"is_method":false,"is_async":false,"decorators":[],"line_number":1012,"language":"rust"},{"name":"calibrator_config_isotonic_roundtrip","params":[],"return_type":null,"docstring":null,"is_method":false,"is_async":false,"decorators":[],"line_number":1023,"language":"rust"},{"name":"calibrator_config_tagged_json","params":[],"return_type":null,"docstring":null,"is_method":false,"is_async":false,"decorators":[],"line_number":1035,"language":"rust"},{"name":"calibrator_trait_is_object_safe","params":[],"return_type":null,"docstring":null,"is_method":false,"is_async":false,"decorators":[],"line_number":1045,"language":"rust"},{"name":"calibrator_via_dyn_dispatch","params":[],"return_type":null,"docstring":null,"is_method":false,"is_async":false,"decorators":[],"line_number":1050,"language":"rust"},{"name":"calibrate_scores_with_labels_identity_passthrough","params":[],"return_type":null,"docstring":null,"is_method":false,"is_async":false,"decorators":[],"line_number":1067,"language":"rust"},{"name":"calibrate_scores_with_labels_reduces_ece_with_isotonic_fit","params":[],"return_type":null,"docstring":null,"is_method":false,"is_async":false,"decorators":[],"line_number":1082,"language":"rust"},{"name":"calibrate_scores_with_labels_emits_scores_calibrated_log","params":[],"return_type":null,"docstring":null,"is_method":false,"is_async":false,"decorators":[],"line_number":1100,"language":"rust"}],"call_graph":{"calls":{"(TemperatureScaling) calibrate":["sigmoid"],"(PlattScaling) calibrate":["sigmoid"],"(CalibratorConfig) calibrate":["calibrate","as_calibrator"],"(CalibratorConfig) name":["name","as_calibrator"],"calibrate_scores_with_labels":["compute_ece","compute_brier_score","bounded_probability"],"temperature_higher_t_softer_output":["calibrate"],"batch_calibration_matches_sequential":["calibrate"],"ece_well_calibrated":["compute_ece"],"ece_completely_miscalibrated":["compute_ece"],"calibrator_config_platt_roundtrip":["calibrate"],"calibrator_via_dyn_dispatch":["calibrate"],"calibrate_scores_with_labels_identity_passthrough":["calibrate_scores_with_labels"],"calibrate_scores_with_labels_reduces_ece_with_isotonic_fit":["calibrate_scores_with_labels"],"calibrate_scores_with_labels_emits_scores_calibrated_log":["calibrate_scores_with_labels"]},"called_by":{"sigmoid":["(TemperatureScaling) calibrate","(PlattScaling) calibrate"],"calibrate":["(CalibratorConfig) calibrate","temperature_higher_t_softer_output","batch_calibration_matches_sequential","calibrator_config_platt_roundtrip","calibrator_via_dyn_dispatch"],"as_calibrator":["(CalibratorConfig) calibrate","(CalibratorConfig) name"],"name":["(CalibratorConfig) name"],"compute_ece":["calibrate_scores_with_labels","ece_well_calibrated","ece_completely_miscalibrated"],"compute_brier_score":["calibrate_scores_with_labels"],"bounded_probability":["calibrate_scores_with_labels"],"calibrate_scores_with_labels":["calibrate_scores_with_labels_identity_passthrough","calibrate_scores_with_labels_reduces_ece_with_isotonic_fit","calibrate_scores_with_labels_emits_scores_calibrated_log"]}}}}