{"mtime_ns":1772149584256654200,"size":22070,"module_info":{"file_path":"/home/mk/projects/Demarch/apps/Autarch/internal/coldwine/cli/commands/mail_test.go","language":"go","docstring":null,"imports":[{"module":"bytes","names":[],"is_from":false,"line_number":4},{"module":"encoding/json","names":[],"is_from":false,"line_number":5},{"module":"os","names":[],"is_from":false,"line_number":6},{"module":"path/filepath","names":[],"is_from":false,"line_number":7},{"module":"strings","names":[],"is_from":false,"line_number":8},{"module":"testing","names":[],"is_from":false,"line_number":9},{"module":"github.com/mistakeknot/autarch/internal/coldwine/project","names":[],"is_from":false,"line_number":11},{"module":"github.com/mistakeknot/autarch/internal/coldwine/storage","names":[],"is_from":false,"line_number":12}],"classes":[],"functions":[{"name":"TestMailSendAndInbox","params":["t *testing.T"],"return_type":null,"docstring":null,"is_method":false,"is_async":false,"decorators":[],"line_number":15,"language":"go"},{"name":"TestMailSendCcBcc","params":["t *testing.T"],"return_type":null,"docstring":null,"is_method":false,"is_async":false,"decorators":[],"line_number":49,"language":"go"},{"name":"TestMailInboxUrgentOnly","params":["t *testing.T"],"return_type":null,"docstring":null,"is_method":false,"is_async":false,"decorators":[],"line_number":93,"language":"go"},{"name":"TestMailInboxSinceFilters","params":["t *testing.T"],"return_type":null,"docstring":null,"is_method":false,"is_async":false,"decorators":[],"line_number":133,"language":"go"},{"name":"TestMailInboxJSONOutput","params":["t *testing.T"],"return_type":null,"docstring":null,"is_method":false,"is_async":false,"decorators":[],"line_number":166,"language":"go"},{"name":"TestMailSendWithAttachments","params":["t *testing.T"],"return_type":null,"docstring":null,"is_method":false,"is_async":false,"decorators":[],"line_number":208,"language":"go"},{"name":"TestMailCommandUsage","params":["t *testing.T"],"return_type":null,"docstring":null,"is_method":false,"is_async":false,"decorators":[],"line_number":251,"language":"go"},{"name":"TestMailSendRequiresRecipient","params":["t *testing.T"],"return_type":null,"docstring":null,"is_method":false,"is_async":false,"decorators":[],"line_number":257,"language":"go"},{"name":"TestMailSendWritesStateDB","params":["t *testing.T"],"return_type":null,"docstring":null,"is_method":false,"is_async":false,"decorators":[],"line_number":279,"language":"go"},{"name":"TestMailContactPolicy","params":["t *testing.T"],"return_type":null,"docstring":null,"is_method":false,"is_async":false,"decorators":[],"line_number":304,"language":"go"},{"name":"TestMailInboxJsonIncludesRecipientMetadata","params":["t *testing.T"],"return_type":null,"docstring":null,"is_method":false,"is_async":false,"decorators":[],"line_number":354,"language":"go"},{"name":"TestMailSearchPaginationJson","params":["t *testing.T"],"return_type":null,"docstring":null,"is_method":false,"is_async":false,"decorators":[],"line_number":401,"language":"go"},{"name":"TestMailSummarizeThreadLLM","params":["t *testing.T"],"return_type":null,"docstring":null,"is_method":false,"is_async":false,"decorators":[],"line_number":444,"language":"go"},{"name":"TestMailSummarizeDryRunUsesLLM","params":["t *testing.T"],"return_type":null,"docstring":null,"is_method":false,"is_async":false,"decorators":[],"line_number":498,"language":"go"},{"name":"TestMailReplyDefaults","params":["t *testing.T"],"return_type":null,"docstring":null,"is_method":false,"is_async":false,"decorators":[],"line_number":545,"language":"go"},{"name":"TestMailSummarizeDryRunInvalidOutput","params":["t *testing.T"],"return_type":null,"docstring":null,"is_method":false,"is_async":false,"decorators":[],"line_number":619,"language":"go"},{"name":"TestMailSummarizeLLMInvalidOutput","params":["t *testing.T"],"return_type":null,"docstring":null,"is_method":false,"is_async":false,"decorators":[],"line_number":654,"language":"go"},{"name":"TestMailCommandErrorWrapping","params":["t *testing.T"],"return_type":null,"docstring":null,"is_method":false,"is_async":false,"decorators":[],"line_number":699,"language":"go"},{"name":"TestMailInboxPlainTextIncludesNextToken","params":["t *testing.T"],"return_type":null,"docstring":null,"is_method":false,"is_async":false,"decorators":[],"line_number":744,"language":"go"}],"call_graph":{"calls":{},"called_by":{}}}}