{"mtime_ns":1772211685841485134,"size":10995,"module_info":{"file_path":"/home/mk/projects/Demarch/research/flywheel_gateway/packages/shared/src/api/response-utils.ts","language":"typescript","docstring":null,"imports":[{"module":"{ AI_HINTS } from \"../errors/ai-hints\"","names":[],"is_from":false,"line_number":9},{"module":"type { ErrorCode } from \"../errors/codes\"","names":[],"is_from":false,"line_number":10},{"module":"{\n  type ApiError,\n  type ApiErrorResponse,\n  type ApiListResponse,\n  type ApiResponse,\n  deriveErrorCategory,\n  type ErrorCategory,\n} from \"./envelope\"","names":[],"is_from":false,"line_number":11}],"classes":[],"functions":[{"name":"generateRequestId","params":[],"return_type":"string","docstring":null,"is_method":false,"is_async":false,"decorators":[],"line_number":28,"language":"typescript"},{"name":"wrapResource","params":["objectType: string","data: T","options: WrapResourceOptions = {}"],"return_type":"ApiResponse<T>","docstring":null,"is_method":false,"is_async":false,"decorators":[],"line_number":71,"language":"typescript"},{"name":"wrapList","params":["data: T[]","options: WrapListOptions"],"return_type":"ApiListResponse<T>","docstring":null,"is_method":false,"is_async":false,"decorators":[],"line_number":134,"language":"typescript"},{"name":"wrapError","params":["options: WrapErrorOptions"],"return_type":"ApiErrorResponse","docstring":null,"is_method":false,"is_async":false,"decorators":[],"line_number":225,"language":"typescript"},{"name":"wrapCreated","params":["objectType: string","data: T","selfUrl: string","options: Omit<WrapResourceOptions, \"links\"> = {}"],"return_type":"ApiResponse<T>","docstring":null,"is_method":false,"is_async":false,"decorators":[],"line_number":300,"language":"typescript"},{"name":"wrapEmptyList","params":["url: string","options: Omit<WrapListOptions, \"url\" | \"hasMore\"> = {}"],"return_type":"ApiListResponse<T>","docstring":null,"is_method":false,"is_async":false,"decorators":[],"line_number":319,"language":"typescript"},{"name":"wrapValidationError","params":["errors: Array<{ path: string; message: string; code?: string }>","options: Pick<WrapErrorOptions, \"requestId\" | \"timestamp\"> = {}"],"return_type":"ApiErrorResponse","docstring":null,"is_method":false,"is_async":false,"decorators":[],"line_number":338,"language":"typescript"},{"name":"wrapNotFound","params":["resourceType: string","identifier: string","options: Pick<WrapErrorOptions, \"requestId\" | \"timestamp\"> = {}"],"return_type":"ApiErrorResponse","docstring":null,"is_method":false,"is_async":false,"decorators":[],"line_number":373,"language":"typescript"}],"call_graph":{"calls":{"wrapResource":["generateRequestId"],"wrapList":["generateRequestId"],"wrapError":["generateRequestId"],"wrapCreated":["wrapResource"],"wrapEmptyList":["wrapList"],"wrapValidationError":["wrapError"],"wrapNotFound":["wrapError"]},"called_by":{"generateRequestId":["wrapResource","wrapList","wrapError"],"wrapResource":["wrapCreated"],"wrapList":["wrapEmptyList"],"wrapError":["wrapValidationError","wrapNotFound"]}}}}