{"mtime_ns":1772149583855654445,"size":5362,"module_info":{"file_path":"/home/mk/projects/Demarch/apps/Autarch/internal/autarch/agent/scan_validate_legacy.go","language":"go","docstring":null,"imports":[{"module":"encoding/json","names":[],"is_from":false,"line_number":4},{"module":"sort","names":[],"is_from":false,"line_number":5},{"module":"strings","names":[],"is_from":false,"line_number":6}],"classes":[{"name":"fileEvidenceLookup","bases":[],"docstring":null,"methods":[],"decorators":[],"line_number":78}],"functions":[{"name":"ValidateLegacyScanResult","params":["result *ScanResult","files map[string]string"],"return_type":null,"docstring":null,"is_method":false,"is_async":false,"decorators":[],"line_number":11,"language":"go"},{"name":"validatePhaseArtifact","params":["phase string","artifact any","lookup EvidenceLookup"],"return_type":null,"docstring":null,"is_method":false,"is_async":false,"decorators":[],"line_number":69,"language":"go"},{"name":"(l fileEvidenceLookup) Exists","params":["path string"],"return_type":"bool","docstring":null,"is_method":true,"is_async":false,"decorators":[],"line_number":82,"language":"go"},{"name":"(l fileEvidenceLookup) ContainsQuote","params":["path, quote string"],"return_type":"bool","docstring":null,"is_method":true,"is_async":false,"decorators":[],"line_number":87,"language":"go"},{"name":"buildEvidenceFromFiles","params":["files map[string]string"],"return_type":null,"docstring":null,"is_method":false,"is_async":false,"decorators":[],"line_number":103,"language":"go"},{"name":"firstEvidenceQuote","params":["content string"],"return_type":"string","docstring":null,"is_method":false,"is_async":false,"decorators":[],"line_number":134,"language":"go"},{"name":"truncateQuote","params":["value string","limit int"],"return_type":"string","docstring":null,"is_method":false,"is_async":false,"decorators":[],"line_number":148,"language":"go"},{"name":"normalizeEvidenceText","params":["value string"],"return_type":"string","docstring":null,"is_method":false,"is_async":false,"decorators":[],"line_number":155,"language":"go"},{"name":"firstNonEmpty","params":[],"return_type":"string","docstring":null,"is_method":false,"is_async":false,"decorators":[],"line_number":177,"language":"go"},{"name":"legacyGoals","params":["result *ScanResult"],"return_type":null,"docstring":null,"is_method":false,"is_async":false,"decorators":[],"line_number":186,"language":"go"},{"name":"legacyPainPoints","params":["result *ScanResult","fallback string"],"return_type":null,"docstring":null,"is_method":false,"is_async":false,"decorators":[],"line_number":202,"language":"go"},{"name":"legacyPersonas","params":["result *ScanResult","fallback string"],"return_type":null,"docstring":null,"is_method":false,"is_async":false,"decorators":[],"line_number":215,"language":"go"}],"call_graph":{"calls":{"ValidateLegacyScanResult":["buildEvidenceFromFiles","firstNonEmpty","legacyGoals","validatePhaseArtifact","legacyPainPoints","legacyPersonas"],"(l fileEvidenceLookup) ContainsQuote":["normalizeEvidenceText"],"buildEvidenceFromFiles":["firstEvidenceQuote"],"firstEvidenceQuote":["truncateQuote"],"legacyPersonas":["firstNonEmpty"]},"called_by":{"buildEvidenceFromFiles":["ValidateLegacyScanResult"],"firstNonEmpty":["ValidateLegacyScanResult","legacyPersonas"],"legacyGoals":["ValidateLegacyScanResult"],"validatePhaseArtifact":["ValidateLegacyScanResult"],"legacyPainPoints":["ValidateLegacyScanResult"],"legacyPersonas":["ValidateLegacyScanResult"],"normalizeEvidenceText":["(l fileEvidenceLookup) ContainsQuote"],"firstEvidenceQuote":["buildEvidenceFromFiles"],"truncateQuote":["firstEvidenceQuote"]}}}}