{"mtime_ns":1772211515231471596,"size":10890,"module_info":{"file_path":"/home/mk/projects/Demarch/research/ntm/internal/tui/styles/badges_test.go","language":"go","docstring":null,"imports":[{"module":"fmt","names":[],"is_from":false,"line_number":4},{"module":"strings","names":[],"is_from":false,"line_number":5},{"module":"testing","names":[],"is_from":false,"line_number":6},{"module":"github.com/charmbracelet/lipgloss","names":[],"is_from":false,"line_number":8}],"classes":[],"functions":[{"name":"TestAgentBadge","params":["t *testing.T"],"return_type":null,"docstring":null,"is_method":false,"is_async":false,"decorators":[],"line_number":11,"language":"go"},{"name":"TestAgentBadgeWithCount","params":["t *testing.T"],"return_type":null,"docstring":null,"is_method":false,"is_async":false,"decorators":[],"line_number":40,"language":"go"},{"name":"TestStatusBadge","params":["t *testing.T"],"return_type":null,"docstring":null,"is_method":false,"is_async":false,"decorators":[],"line_number":61,"language":"go"},{"name":"TestStatusBadgeIcon","params":["t *testing.T"],"return_type":null,"docstring":null,"is_method":false,"is_async":false,"decorators":[],"line_number":84,"language":"go"},{"name":"TestPriorityBadge","params":["t *testing.T"],"return_type":null,"docstring":null,"is_method":false,"is_async":false,"decorators":[],"line_number":99,"language":"go"},{"name":"TestCountBadge","params":["t *testing.T"],"return_type":null,"docstring":null,"is_method":false,"is_async":false,"decorators":[],"line_number":117,"language":"go"},{"name":"TestHealthBadge","params":["t *testing.T"],"return_type":null,"docstring":null,"is_method":false,"is_async":false,"decorators":[],"line_number":135,"language":"go"},{"name":"TestIssueTypeBadge","params":["t *testing.T"],"return_type":null,"docstring":null,"is_method":false,"is_async":false,"decorators":[],"line_number":150,"language":"go"},{"name":"TestModelBadge","params":["t *testing.T"],"return_type":null,"docstring":null,"is_method":false,"is_async":false,"decorators":[],"line_number":169,"language":"go"},{"name":"TestTokenVelocityBadge","params":["t *testing.T"],"return_type":null,"docstring":null,"is_method":false,"is_async":false,"decorators":[],"line_number":193,"language":"go"},{"name":"TestTokensPerSecondBadge","params":["t *testing.T"],"return_type":null,"docstring":null,"is_method":false,"is_async":false,"decorators":[],"line_number":206,"language":"go"},{"name":"TestMemoryUsageBadge","params":["t *testing.T"],"return_type":null,"docstring":null,"is_method":false,"is_async":false,"decorators":[],"line_number":219,"language":"go"},{"name":"TestAlertSeverityBadge","params":["t *testing.T"],"return_type":null,"docstring":null,"is_method":false,"is_async":false,"decorators":[],"line_number":229,"language":"go"},{"name":"severityLabel","params":["sev string"],"return_type":"string","docstring":null,"is_method":false,"is_async":false,"decorators":[],"line_number":245,"language":"go"},{"name":"TestBadgeOptions","params":["t *testing.T"],"return_type":null,"docstring":null,"is_method":false,"is_async":false,"decorators":[],"line_number":262,"language":"go"},{"name":"TestBadgeGroup","params":["t *testing.T"],"return_type":null,"docstring":null,"is_method":false,"is_async":false,"decorators":[],"line_number":278,"language":"go"},{"name":"TestBadgeBar","params":["t *testing.T"],"return_type":null,"docstring":null,"is_method":false,"is_async":false,"decorators":[],"line_number":293,"language":"go"},{"name":"TestTextBadge","params":["t *testing.T"],"return_type":null,"docstring":null,"is_method":false,"is_async":false,"decorators":[],"line_number":307,"language":"go"},{"name":"TestMiniBar","params":["t *testing.T"],"return_type":null,"docstring":null,"is_method":false,"is_async":false,"decorators":[],"line_number":317,"language":"go"},{"name":"TestRankBadge","params":["t *testing.T"],"return_type":null,"docstring":null,"is_method":false,"is_async":false,"decorators":[],"line_number":341,"language":"go"},{"name":"TestFixedWidthBadge","params":["t *testing.T"],"return_type":null,"docstring":null,"is_method":false,"is_async":false,"decorators":[],"line_number":357,"language":"go"},{"name":"TestTruncateBadgeText","params":["t *testing.T"],"return_type":null,"docstring":null,"is_method":false,"is_async":false,"decorators":[],"line_number":387,"language":"go"},{"name":"TestTruncateToWidth_AllRunesExhausted","params":["t *testing.T"],"return_type":null,"docstring":null,"is_method":false,"is_async":false,"decorators":[],"line_number":414,"language":"go"},{"name":"TestModelBadgeWidthConstant","params":["t *testing.T"],"return_type":null,"docstring":null,"is_method":false,"is_async":false,"decorators":[],"line_number":424,"language":"go"}],"call_graph":{"calls":{"TestAlertSeverityBadge":["severityLabel"]},"called_by":{"severityLabel":["TestAlertSeverityBadge"]}}}}