{"mtime_ns":1772211656351482241,"size":19175,"module_info":{"file_path":"/home/mk/projects/Demarch/research/cross_agent_session_resumer/src/main.rs","language":"rust","docstring":null,"imports":[{"module":"std::path::PathBuf","names":[],"is_from":false,"line_number":7},{"module":"std::process::ExitCode","names":[],"is_from":false,"line_number":8},{"module":"clap::Parser","names":[],"is_from":false,"line_number":10},{"module":"colored::Colorize","names":[],"is_from":false,"line_number":11},{"module":"tracing_subscriber::EnvFilter","names":[],"is_from":false,"line_number":12},{"module":"casr::discovery::ProviderRegistry","names":[],"is_from":false,"line_number":14},{"module":"casr::model::truncate_title","names":[],"is_from":false,"line_number":15},{"module":"casr::pipeline::{ConversionPipeline, ConvertOptions}","names":[],"is_from":false,"line_number":16}],"classes":[{"name":"Cli","bases":[],"docstring":null,"methods":[],"decorators":[],"line_number":29}],"functions":[{"name":"long_version","params":[],"return_type":"&'static str","docstring":null,"is_method":false,"is_async":false,"decorators":[],"line_number":111,"language":"rust"},{"name":"init_tracing","params":["cli: &Cli"],"return_type":null,"docstring":null,"is_method":false,"is_async":false,"decorators":[],"line_number":127,"language":"rust"},{"name":"main","params":[],"return_type":"ExitCode","docstring":null,"is_method":false,"is_async":false,"decorators":[],"line_number":143,"language":"rust"},{"name":"error_type_name","params":["e: &anyhow::Error"],"return_type":"&'static str","docstring":null,"is_method":false,"is_async":false,"decorators":[],"line_number":203,"language":"rust"},{"name":"cmd_resume","params":["target: &str","session_id: &str","dry_run: bool","force: bool","source: Option<String>","enrich: bool","json_mode: bool"],"return_type":"anyhow::Result<()>","docstring":null,"is_method":false,"is_async":false,"decorators":[],"line_number":225,"language":"rust"},{"name":"cmd_list","params":["provider_filter: Option<&str>","workspace_filter: Option<&str>","limit: usize","sort: &str","json_mode: bool"],"return_type":"anyhow::Result<()>","docstring":null,"is_method":false,"is_async":false,"decorators":[],"line_number":311,"language":"rust"},{"name":"cmd_info","params":["session_id: &str","json_mode: bool"],"return_type":"anyhow::Result<()>","docstring":null,"is_method":false,"is_async":false,"decorators":[],"line_number":498,"language":"rust"},{"name":"cmd_providers","params":["json_mode: bool"],"return_type":"anyhow::Result<()>","docstring":null,"is_method":false,"is_async":false,"decorators":[],"line_number":553,"language":"rust"},{"name":"cmd_completions","params":["shell: &str"],"return_type":"anyhow::Result<()>","docstring":null,"is_method":false,"is_async":false,"decorators":[],"line_number":595,"language":"rust"}],"call_graph":{"calls":{"main":["init_tracing","cmd_resume","cmd_list","cmd_info","cmd_providers","cmd_completions"]},"called_by":{"init_tracing":["main"],"cmd_resume":["main"],"cmd_list":["main"],"cmd_info":["main"],"cmd_providers":["main"],"cmd_completions":["main"]}}}}