{"mtime_ns":1772211651786481812,"size":45657,"module_info":{"file_path":"/home/mk/projects/Demarch/research/frankensearch/crates/frankensearch-fusion/src/interaction_lanes.rs","language":"rust","docstring":null,"imports":[{"module":"std::fmt","names":[],"is_from":false,"line_number":16},{"module":"serde::{Deserialize, Serialize}","names":[],"is_from":false,"line_number":18},{"module":"frankensearch_core::QueryClass","names":[],"is_from":false,"line_number":20},{"module":"super::*","names":[],"is_from":false,"line_number":862}],"classes":[{"name":"FeatureToggles","bases":[],"docstring":null,"methods":[],"decorators":[],"line_number":27},{"name":"QuerySlice","bases":[],"docstring":null,"methods":[],"decorators":[],"line_number":197},{"name":"InteractionLane","bases":[],"docstring":null,"methods":[],"decorators":[],"line_number":250},{"name":"FixtureQuery","bases":[],"docstring":null,"methods":[],"decorators":[],"line_number":817}],"functions":[{"name":"(FeatureToggles) default","params":[],"return_type":"Self","docstring":null,"is_method":true,"is_async":false,"decorators":[],"line_number":64,"language":"rust"},{"name":"(FeatureToggles) active_count","params":["&self"],"return_type":"usize","docstring":null,"is_method":true,"is_async":false,"decorators":[],"line_number":82,"language":"rust"},{"name":"(CorpusSlice) id_prefix","params":["self"],"return_type":"&'static str","docstring":null,"is_method":true,"is_async":false,"decorators":[],"line_number":143,"language":"rust"},{"name":"(CorpusSlice) id_prefixes","params":["self"],"return_type":"&'static [&'static str]","docstring":null,"is_method":true,"is_async":false,"decorators":[],"line_number":157,"language":"rust"},{"name":"(CorpusSlice) matches_doc_id","params":["self","doc_id: &str"],"return_type":"bool","docstring":null,"is_method":true,"is_async":false,"decorators":[],"line_number":176,"language":"rust"},{"name":"(CorpusSlice) approx_count","params":["self"],"return_type":"usize","docstring":null,"is_method":true,"is_async":false,"decorators":[],"line_number":187,"language":"rust"},{"name":"(QuerySlice) default","params":[],"return_type":"Self","docstring":null,"is_method":true,"is_async":false,"decorators":[],"line_number":207,"language":"rust"},{"name":"(InteractionLane) fmt","params":["&self","f: &mut fmt::Formatter<'_>"],"return_type":"fmt::Result","docstring":null,"is_method":true,"is_async":false,"decorators":[],"line_number":272,"language":"rust"},{"name":"lane_catalog","params":[],"return_type":"Vec<InteractionLane>","docstring":null,"is_method":false,"is_async":false,"decorators":[],"line_number":667,"language":"rust"},{"name":"lane_with_default_query_slice","params":["mut lane: InteractionLane"],"return_type":"InteractionLane","docstring":null,"is_method":false,"is_async":false,"decorators":[],"line_number":693,"language":"rust"},{"name":"lane_ids","params":[],"return_type":"Vec<&'static str>","docstring":null,"is_method":false,"is_async":false,"decorators":[],"line_number":706,"language":"rust"},{"name":"lane_by_id","params":["id: &str"],"return_type":"Option<InteractionLane>","docstring":null,"is_method":false,"is_async":false,"decorators":[],"line_number":712,"language":"rust"},{"name":"lanes_at_risk","params":["min_risk: RiskLevel"],"return_type":"Vec<InteractionLane>","docstring":null,"is_method":false,"is_async":false,"decorators":[],"line_number":718,"language":"rust"},{"name":"fixture_queries","params":[],"return_type":"Vec<FixtureQuery>","docstring":null,"is_method":false,"is_async":false,"decorators":[],"line_number":731,"language":"rust"},{"name":"(FixtureQuery) query_for_lane","params":["&self","include_negated: bool"],"return_type":"&str","docstring":null,"is_method":true,"is_async":false,"decorators":[],"line_number":830,"language":"rust"},{"name":"queries_for_lane","params":["lane: &InteractionLane"],"return_type":"Vec<FixtureQuery>","docstring":null,"is_method":false,"is_async":false,"decorators":[],"line_number":841,"language":"rust"},{"name":"derive_query_seed","params":["lane_seed: u64","query_index: usize"],"return_type":"u64","docstring":null,"is_method":false,"is_async":false,"decorators":[],"line_number":855,"language":"rust"},{"name":"catalog_has_expected_lane_count","params":[],"return_type":null,"docstring":null,"is_method":false,"is_async":false,"decorators":[],"line_number":865,"language":"rust"},{"name":"all_lane_ids_are_unique","params":[],"return_type":null,"docstring":null,"is_method":false,"is_async":false,"decorators":[],"line_number":871,"language":"rust"},{"name":"all_lane_seeds_are_unique","params":[],"return_type":null,"docstring":null,"is_method":false,"is_async":false,"decorators":[],"line_number":880,"language":"rust"},{"name":"catalog_sorted_by_risk_descending","params":[],"return_type":null,"docstring":null,"is_method":false,"is_async":false,"decorators":[],"line_number":893,"language":"rust"},{"name":"baseline_lane_has_default_toggles","params":[],"return_type":null,"docstring":null,"is_method":false,"is_async":false,"decorators":[],"line_number":908,"language":"rust"},{"name":"kitchen_sink_has_all_features_active","params":[],"return_type":null,"docstring":null,"is_method":false,"is_async":false,"decorators":[],"line_number":916,"language":"rust"},{"name":"lane_by_id_returns_none_for_unknown","params":[],"return_type":null,"docstring":null,"is_method":false,"is_async":false,"decorators":[],"line_number":930,"language":"rust"},{"name":"high_risk_lanes_include_expected_compositions","params":[],"return_type":null,"docstring":null,"is_method":false,"is_async":false,"decorators":[],"line_number":935,"language":"rust"},{"name":"fixture_queries_cover_all_non_empty_classes","params":[],"return_type":null,"docstring":null,"is_method":false,"is_async":false,"decorators":[],"line_number":965,"language":"rust"},{"name":"fixture_queries_have_negated_variants","params":[],"return_type":null,"docstring":null,"is_method":false,"is_async":false,"decorators":[],"line_number":976,"language":"rust"},{"name":"queries_for_lane_filters_correctly","params":[],"return_type":null,"docstring":null,"is_method":false,"is_async":false,"decorators":[],"line_number":989,"language":"rust"},{"name":"query_for_lane_selects_negated_when_active","params":[],"return_type":null,"docstring":null,"is_method":false,"is_async":false,"decorators":[],"line_number":1001,"language":"rust"},{"name":"query_for_lane_falls_back_when_no_negation","params":[],"return_type":null,"docstring":null,"is_method":false,"is_async":false,"decorators":[],"line_number":1012,"language":"rust"},{"name":"derive_query_seed_is_deterministic","params":[],"return_type":null,"docstring":null,"is_method":false,"is_async":false,"decorators":[],"line_number":1023,"language":"rust"},{"name":"derive_query_seed_differs_per_index","params":[],"return_type":null,"docstring":null,"is_method":false,"is_async":false,"decorators":[],"line_number":1030,"language":"rust"},{"name":"derive_query_seed_differs_per_lane","params":[],"return_type":null,"docstring":null,"is_method":false,"is_async":false,"decorators":[],"line_number":1040,"language":"rust"},{"name":"corpus_slice_id_prefix_non_empty_for_clusters","params":[],"return_type":null,"docstring":null,"is_method":false,"is_async":false,"decorators":[],"line_number":1047,"language":"rust"},{"name":"corpus_slice_counts_sum_correctly","params":[],"return_type":null,"docstring":null,"is_method":false,"is_async":false,"decorators":[],"line_number":1061,"language":"rust"},{"name":"supplemental_slice_matches_all_prefixes","params":[],"return_type":null,"docstring":null,"is_method":false,"is_async":false,"decorators":[],"line_number":1081,"language":"rust"},{"name":"feature_toggles_active_count_zero_for_default","params":[],"return_type":null,"docstring":null,"is_method":false,"is_async":false,"decorators":[],"line_number":1091,"language":"rust"},{"name":"feature_toggles_active_count_matches_toggles","params":[],"return_type":null,"docstring":null,"is_method":false,"is_async":false,"decorators":[],"line_number":1096,"language":"rust"},{"name":"all_lanes_have_bead_refs","params":[],"return_type":null,"docstring":null,"is_method":false,"is_async":false,"decorators":[],"line_number":1106,"language":"rust"},{"name":"all_lanes_have_corpus_slices","params":[],"return_type":null,"docstring":null,"is_method":false,"is_async":false,"decorators":[],"line_number":1120,"language":"rust"},{"name":"negation_lanes_have_negation_queries_toggle","params":[],"return_type":null,"docstring":null,"is_method":false,"is_async":false,"decorators":[],"line_number":1131,"language":"rust"},{"name":"display_format_includes_lane_id","params":[],"return_type":null,"docstring":null,"is_method":false,"is_async":false,"decorators":[],"line_number":1144,"language":"rust"},{"name":"serde_roundtrip_lane","params":[],"return_type":null,"docstring":null,"is_method":false,"is_async":false,"decorators":[],"line_number":1152,"language":"rust"},{"name":"serde_roundtrip_feature_toggles","params":[],"return_type":null,"docstring":null,"is_method":false,"is_async":false,"decorators":[],"line_number":1169,"language":"rust"},{"name":"calibrator_choice_all_variants_serialize","params":[],"return_type":null,"docstring":null,"is_method":false,"is_async":false,"decorators":[],"line_number":1187,"language":"rust"},{"name":"corpus_slice_full_matches_any_doc_id","params":[],"return_type":null,"docstring":null,"is_method":false,"is_async":false,"decorators":[],"line_number":1203,"language":"rust"},{"name":"corpus_slice_full_id_prefixes_empty","params":[],"return_type":null,"docstring":null,"is_method":false,"is_async":false,"decorators":[],"line_number":1211,"language":"rust"},{"name":"corpus_slice_no_cross_match","params":[],"return_type":null,"docstring":null,"is_method":false,"is_async":false,"decorators":[],"line_number":1216,"language":"rust"},{"name":"risk_level_ordering","params":[],"return_type":null,"docstring":null,"is_method":false,"is_async":false,"decorators":[],"line_number":1225,"language":"rust"},{"name":"calibrator_choice_hash_in_set","params":[],"return_type":null,"docstring":null,"is_method":false,"is_async":false,"decorators":[],"line_number":1232,"language":"rust"},{"name":"query_slice_default_values","params":[],"return_type":null,"docstring":null,"is_method":false,"is_async":false,"decorators":[],"line_number":1246,"language":"rust"},{"name":"feature_toggles_active_count_circuit_breaker_off","params":[],"return_type":null,"docstring":null,"is_method":false,"is_async":false,"decorators":[],"line_number":1254,"language":"rust"},{"name":"feature_toggles_active_count_all_toggled","params":[],"return_type":null,"docstring":null,"is_method":false,"is_async":false,"decorators":[],"line_number":1264,"language":"rust"},{"name":"lanes_at_risk_low_returns_all","params":[],"return_type":null,"docstring":null,"is_method":false,"is_async":false,"decorators":[],"line_number":1281,"language":"rust"},{"name":"lanes_at_risk_medium_excludes_low","params":[],"return_type":null,"docstring":null,"is_method":false,"is_async":false,"decorators":[],"line_number":1287,"language":"rust"},{"name":"expected_phase_serde_roundtrip","params":[],"return_type":null,"docstring":null,"is_method":false,"is_async":false,"decorators":[],"line_number":1301,"language":"rust"},{"name":"risk_level_serde_roundtrip","params":[],"return_type":null,"docstring":null,"is_method":false,"is_async":false,"decorators":[],"line_number":1314,"language":"rust"}],"call_graph":{"calls":{"(CorpusSlice) matches_doc_id":["id_prefixes"],"lane_ids":["lane_catalog"],"lane_by_id":["lane_catalog"],"lanes_at_risk":["lane_catalog"],"queries_for_lane":["fixture_queries"],"catalog_has_expected_lane_count":["lane_catalog"],"all_lane_ids_are_unique":["lane_ids"],"all_lane_seeds_are_unique":["lane_catalog"],"catalog_sorted_by_risk_descending":["lane_catalog"],"baseline_lane_has_default_toggles":["lane_by_id"],"kitchen_sink_has_all_features_active":["lane_by_id"],"high_risk_lanes_include_expected_compositions":["lanes_at_risk"],"fixture_queries_cover_all_non_empty_classes":["fixture_queries"],"fixture_queries_have_negated_variants":["fixture_queries"],"queries_for_lane_filters_correctly":["lane_by_id","queries_for_lane"],"derive_query_seed_is_deterministic":["derive_query_seed"],"derive_query_seed_differs_per_index":["derive_query_seed"],"derive_query_seed_differs_per_lane":["derive_query_seed"],"corpus_slice_counts_sum_correctly":["approx_count"],"all_lanes_have_bead_refs":["lane_catalog"],"all_lanes_have_corpus_slices":["lane_catalog"],"negation_lanes_have_negation_queries_toggle":["lane_catalog"],"display_format_includes_lane_id":["lane_by_id"],"serde_roundtrip_lane":["lane_catalog"],"lanes_at_risk_low_returns_all":["lanes_at_risk"],"lanes_at_risk_medium_excludes_low":["lanes_at_risk"]},"called_by":{"id_prefixes":["(CorpusSlice) matches_doc_id"],"lane_catalog":["lane_ids","lane_by_id","lanes_at_risk","catalog_has_expected_lane_count","all_lane_seeds_are_unique","catalog_sorted_by_risk_descending","all_lanes_have_bead_refs","all_lanes_have_corpus_slices","negation_lanes_have_negation_queries_toggle","serde_roundtrip_lane"],"fixture_queries":["queries_for_lane","fixture_queries_cover_all_non_empty_classes","fixture_queries_have_negated_variants"],"lane_ids":["all_lane_ids_are_unique"],"lane_by_id":["baseline_lane_has_default_toggles","kitchen_sink_has_all_features_active","queries_for_lane_filters_correctly","display_format_includes_lane_id"],"lanes_at_risk":["high_risk_lanes_include_expected_compositions","lanes_at_risk_low_returns_all","lanes_at_risk_medium_excludes_low"],"queries_for_lane":["queries_for_lane_filters_correctly"],"derive_query_seed":["derive_query_seed_is_deterministic","derive_query_seed_differs_per_index","derive_query_seed_differs_per_lane"],"approx_count":["corpus_slice_counts_sum_correctly"]}}}}