{"mtime_ns":1772211515242471597,"size":31951,"module_info":{"file_path":"/home/mk/projects/Demarch/research/ntm/tests/e2e/multi_session_test.go","language":"go","docstring":null,"imports":[{"module":"context","names":[],"is_from":false,"line_number":4},{"module":"encoding/json","names":[],"is_from":false,"line_number":5},{"module":"fmt","names":[],"is_from":false,"line_number":6},{"module":"os","names":[],"is_from":false,"line_number":7},{"module":"os/exec","names":[],"is_from":false,"line_number":8},{"module":"path/filepath","names":[],"is_from":false,"line_number":9},{"module":"strings","names":[],"is_from":false,"line_number":10},{"module":"sync","names":[],"is_from":false,"line_number":11},{"module":"testing","names":[],"is_from":false,"line_number":12},{"module":"time","names":[],"is_from":false,"line_number":13},{"module":"github.com/Dicklesworthstone/ntm/internal/tmux","names":[],"is_from":false,"line_number":15},{"module":"github.com/Dicklesworthstone/ntm/tests/testutil","names":[],"is_from":false,"line_number":16}],"classes":[],"functions":[{"name":"TestMultiSessionManagement","params":["t *testing.T"],"return_type":null,"docstring":null,"is_method":false,"is_async":false,"decorators":[],"line_number":21,"language":"go"},{"name":"TestConcurrentSessionOperations","params":["t *testing.T"],"return_type":null,"docstring":null,"is_method":false,"is_async":false,"decorators":[],"line_number":226,"language":"go"},{"name":"TestSessionNamespaceIsolation","params":["t *testing.T"],"return_type":null,"docstring":null,"is_method":false,"is_async":false,"decorators":[],"line_number":445,"language":"go"},{"name":"TestRapidSessionCreationDestruction","params":["t *testing.T"],"return_type":null,"docstring":null,"is_method":false,"is_async":false,"decorators":[],"line_number":588,"language":"go"},{"name":"TestCrossSessionRobotSendAck","params":["t *testing.T"],"return_type":null,"docstring":null,"is_method":false,"is_async":false,"decorators":[],"line_number":679,"language":"go"},{"name":"TestConcurrentMultiSessionRobotSendAckStress","params":["t *testing.T"],"return_type":null,"docstring":null,"is_method":false,"is_async":false,"decorators":[],"line_number":849,"language":"go"}],"call_graph":{"calls":{},"called_by":{}}}}