{"mtime_ns":1772211685812485131,"size":9424,"module_info":{"file_path":"/home/mk/projects/Demarch/research/flywheel_gateway/apps/gateway/src/utils/response.ts","language":"typescript","docstring":null,"imports":[{"module":"{\n  type WrapErrorOptions,\n  type WrapListOptions,\n  type WrapResourceOptions,\n  wrapCreated,\n  wrapEmptyList,\n  wrapError,\n  wrapList,\n  wrapNotFound,\n  wrapResource,\n  wrapValidationError,\n} from \"@flywheel/shared\"","names":[],"is_from":false,"line_number":9},{"module":"{\n  type GatewayError,\n  serializeGatewayError,\n} from \"@flywheel/shared/errors\"","names":[],"is_from":false,"line_number":21},{"module":"type { Context } from \"hono\"","names":[],"is_from":false,"line_number":25},{"module":"type { ContentfulStatusCode } from \"hono/utils/http-status\"","names":[],"is_from":false,"line_number":26},{"module":"{ getCorrelationId } from \"../middleware/correlation\"","names":[],"is_from":false,"line_number":27}],"classes":[],"functions":[{"name":"sendResource","params":["c: Context","objectType: string","data: T","status: ContentfulStatusCode = 200","options: Omit<WrapResourceOptions, \"requestId\"> = {}"],"return_type":null,"docstring":null,"is_method":false,"is_async":false,"decorators":[],"line_number":51,"language":"typescript"},{"name":"sendCreated","params":["c: Context","objectType: string","data: T","selfUrl: string","options: Omit<WrapResourceOptions, \"requestId\" | \"links\"> = {}"],"return_type":null,"docstring":null,"is_method":false,"is_async":false,"decorators":[],"line_number":83,"language":"typescript"},{"name":"sendList","params":["c: Context","data: T[]","options: Omit<WrapListOptions, \"url\" | \"requestId\"> = {}"],"return_type":null,"docstring":null,"is_method":false,"is_async":false,"decorators":[],"line_number":117,"language":"typescript"},{"name":"sendEmptyList","params":["c: Context"],"return_type":null,"docstring":null,"is_method":false,"is_async":false,"decorators":[],"line_number":140,"language":"typescript"},{"name":"sendError","params":["c: Context","code: string","message: string","status: ContentfulStatusCode","options: Omit<WrapErrorOptions, \"code\" | \"message\" | \"requestId\"> = {}"],"return_type":null,"docstring":null,"is_method":false,"is_async":false,"decorators":[],"line_number":165,"language":"typescript"},{"name":"sendNotFound","params":["c: Context","resourceType: string","identifier: string"],"return_type":null,"docstring":null,"is_method":false,"is_async":false,"decorators":[],"line_number":191,"language":"typescript"},{"name":"sendValidationError","params":["c: Context","errors: Array<{ path: string; message: string; code?: string }>"],"return_type":null,"docstring":null,"is_method":false,"is_async":false,"decorators":[],"line_number":215,"language":"typescript"},{"name":"sendInternalError","params":["c: Context","message = \"Internal server error\""],"return_type":null,"docstring":null,"is_method":false,"is_async":false,"decorators":[],"line_number":230,"language":"typescript"},{"name":"sendConflict","params":["c: Context","code: string","message: string","options: Omit<WrapErrorOptions, \"code\" | \"message\" | \"requestId\"> = {}"],"return_type":null,"docstring":null,"is_method":false,"is_async":false,"decorators":[],"line_number":256,"language":"typescript"},{"name":"sendForbidden","params":["c: Context","message = \"Access denied\""],"return_type":null,"docstring":null,"is_method":false,"is_async":false,"decorators":[],"line_number":273,"language":"typescript"},{"name":"sendUnauthorized","params":["c: Context","message = \"Authentication required\""],"return_type":null,"docstring":null,"is_method":false,"is_async":false,"decorators":[],"line_number":294,"language":"typescript"},{"name":"sendNoContent","params":["c: Context"],"return_type":null,"docstring":null,"is_method":false,"is_async":false,"decorators":[],"line_number":327,"language":"typescript"},{"name":"sendGatewayError","params":["c: Context","error: GatewayError"],"return_type":null,"docstring":null,"is_method":false,"is_async":false,"decorators":[],"line_number":353,"language":"typescript"}],"call_graph":{"calls":{"sendGatewayError":["sendError"]},"called_by":{"sendError":["sendGatewayError"]}}}}